LICENSE
README.md
setup.py
rliable/__init__.py
rliable/library.py
rliable/metrics.py
rliable/plot_utils.py
rliable_fork.egg-info/PKG-INFO
rliable_fork.egg-info/SOURCES.txt
rliable_fork.egg-info/dependency_links.txt
rliable_fork.egg-info/requires.txt
rliable_fork.egg-info/top_level.txt